setup.cfg
setup.py
./mlenv_cloud/__init__.py
./mlenv_cloud/version.py
./mlenv_cloud/core/__init__.py
./mlenv_cloud/core/containerize.py
./mlenv_cloud/core/docker_config.py
./mlenv_cloud/core/gcp.py
./mlenv_cloud/core/preprocess.py
./mlenv_cloud/core/run.py
./mlenv_cloud/core/validate.py
./mlenv_cloud/utils/__init__.py
./mlenv_cloud/utils/gcs.py
./mlenv_cloud/utils/google_api_client.py
./mlenv_cloud/utils/google_build_client.py
mlenv_cloud.egg-info/PKG-INFO
mlenv_cloud.egg-info/SOURCES.txt
mlenv_cloud.egg-info/dependency_links.txt
mlenv_cloud.egg-info/requires.txt
mlenv_cloud.egg-info/top_level.txt